setup.py
timesketch_api_client/__init__.py
timesketch_api_client/aggregation.py
timesketch_api_client/aggregation_test.py
timesketch_api_client/analyzer.py
timesketch_api_client/cli_input.py
timesketch_api_client/client.py
timesketch_api_client/client_test.py
timesketch_api_client/config.py
timesketch_api_client/config_test.py
timesketch_api_client/credentials.py
timesketch_api_client/crypto.py
timesketch_api_client/definitions.py
timesketch_api_client/error.py
timesketch_api_client/graph.py
timesketch_api_client/graph_test.py
timesketch_api_client/index.py
timesketch_api_client/resource.py
timesketch_api_client/retry_test.py
timesketch_api_client/scenario.py
timesketch_api_client/scenario_test.py
timesketch_api_client/search.py
timesketch_api_client/search_test.py
timesketch_api_client/searchtemplate.py
timesketch_api_client/sigma.py
timesketch_api_client/sigma_test.py
timesketch_api_client/sketch.py
timesketch_api_client/sketch_test.py
timesketch_api_client/story.py
timesketch_api_client/story_test.py
timesketch_api_client/test_lib.py
timesketch_api_client/timeline.py
timesketch_api_client/timeline_test.py
timesketch_api_client/user.py
timesketch_api_client/version.py
timesketch_api_client/view.py
timesketch_api_client/view_test.py
timesketch_api_client.egg-info/PKG-INFO
timesketch_api_client.egg-info/SOURCES.txt
timesketch_api_client.egg-info/dependency_links.txt
timesketch_api_client.egg-info/not-zip-safe
timesketch_api_client.egg-info/requires.txt
timesketch_api_client.egg-info/top_level.txt