Metadata-Version: 2.4
Name: timesketch-api-client
Version: 20251219
Summary: Timesketch API client
Home-page: http://www.timesketch.org/
Maintainer: Timesketch development team
Maintainer-email: timesketch-dev@googlegroups.com
License: Apache License, Version 2.0
Classifier: Development Status :: 4 - Beta
Classifier: Environment :: Console
Classifier: Operating System :: OS Independent
Classifier: Programming Language :: Python
Requires-Dist: altair
Requires-Dist: cryptography
Requires-Dist: pandas
Requires-Dist: google_auth_oauthlib
Requires-Dist: requests
Requires-Dist: beautifulsoup4
Requires-Dist: google-auth
Requires-Dist: networkx
Dynamic: classifier
Dynamic: description
Dynamic: home-page
Dynamic: license
Dynamic: maintainer
Dynamic: maintainer-email
Dynamic: requires-dist
Dynamic: summary
